tests/__init__.py
tests/conftest.py
tests/test_auth_manager.py
tests/test_rate_limiter.py
tests/test_related_strategy.py
tests/test_search_strategy.py
tests/test_spotify_client.py
tests/test_storage.py
verse_jan25_prj/__init__.py
verse_jan25_prj/auth_manager.py
verse_jan25_prj/main.py
verse_jan25_prj/models.py
verse_jan25_prj/rate_limiter.py
verse_jan25_prj/spotify.py
verse_jan25_prj/storage.py
verse_jan25_prj/strategies/__init__.py
verse_jan25_prj/strategies/base_strategy.py
verse_jan25_prj/strategies/related_strategy.py
verse_jan25_prj/strategies/search_strategy.py
verse_jan25_prj-1.1.1.dist-info/METADATA
verse_jan25_prj-1.1.1.dist-info/WHEEL
verse_jan25_prj-1.1.1.dist-info/entry_points.txt
verse_jan25_prj-1.1.1.dist-info/top_level.txt
verse_jan25_prj-1.1.1.dist-info/RECORD
